tatoebatools/__init__.py
tatoebatools/config.py
tatoebatools/datafile.py
tatoebatools/difference.py
tatoebatools/download.py
tatoebatools/download_page.py
tatoebatools/exceptions.py
tatoebatools/jpn_indices.py
tatoebatools/links.py
tatoebatools/models.py
tatoebatools/queries.py
tatoebatools/sentences_base.py
tatoebatools/sentences_cc0.py
tatoebatools/sentences_detailed.py
tatoebatools/sentences_in_lists.py
tatoebatools/sentences_with_audio.py
tatoebatools/table.py
tatoebatools/tags.py
tatoebatools/tatoebatools.py
tatoebatools/transcriptions.py
tatoebatools/update.py
tatoebatools/user_languages.py
tatoebatools/user_lists.py
tatoebatools/utils.py
tatoebatools/version.py
tests/__init__.py
tests/test_datafile.py
tests/test_download_page.py
tests/test_table.py
tests/test_update.py
tests/test_utils.py
tests/test_version.py
tatoebatools-0.2.3.dist-info/METADATA
tatoebatools-0.2.3.dist-info/WHEEL
tatoebatools-0.2.3.dist-info/top_level.txt
tatoebatools-0.2.3.dist-info/RECORD
