Metadata-Version: 2.1
Name: tatoebatools
Version: 0.2.3
Summary: A library for downloading and reading data from Tatoeba
Home-page: https://github.com/LBeaudoux/tatoebatools
Author: L.Beaudoux
Classifier: Programming Language :: Python :: 3
Classifier: Programming Language :: Python :: 3.8
Classifier: Programming Language :: Python :: 3.9
Classifier: Programming Language :: Python :: 3.10
Classifier: Programming Language :: Python :: 3.11
Classifier: Programming Language :: Python :: 3.12
Classifier: License :: OSI Approved :: MIT License
Classifier: Operating System :: OS Independent
Classifier: Development Status :: 4 - Beta
Requires-Python: >=3.8.0
Requires-Dist: beautifulsoup4 >=4.12.2
Requires-Dist: pandas >=2.0.3
Requires-Dist: requests >=2.31.0
Requires-Dist: SQLAlchemy >=2.0.23
Requires-Dist: tqdm >=4.66.1
Requires-Dist: importlib-resources >=6.1.1 ; python_version < "3.9"
